{
  "name": {
    "common": "Comoros",
    "official": "Union of the Comoros",
    "native": {
      "ara": {
        "official": "الاتحاد القمري",
        "common": "جزر القمر"
      },
      "fra": {
        "official": "Union des Comores",
        "common": "Comores"
      },
      "zdj": {
        "official": "Udzima wa Komori",
        "common": "Komori"
      }
    }
  },
  "cca2": "KM",
  "cca3": "COM",
  "ccn3": "174",
  "cioc": "COM",
  "fifa": "COM",
  "tld": [
    ".km"
  ],
  "altSpellings": [
    "KM",
    "Union of the Comoros",
    "Union des Comores",
    "Udzima wa Komori",
    "al-Ittiḥād al-Qumurī"
  ],
  "independent": true,
  "status": "officially-assigned",
  "unMember": true,
  "unRegionalGroup": "African Group",
  "capital": [
    "Moroni"
  ],
  "region": "Africa",
  "subregion": "Eastern Africa",
  "continents": [
    "Africa"
  ],
  "latlng": [
    -12.16666666,
    44.25
  ],
  "landlocked": false,
  "borders": [],
  "area": 1862,
  "population": 919901,
  "demonyms": {
    "eng": {
      "f": "Comoran",
      "m": "Comoran"
    },
    "fra": {
      "f": "Comorienne",
      "m": "Comorien"
    }
  },
  "languages": {
    "ara": "Arabic",
    "fra": "French",
    "zdj": "Comorian"
  },
  "currencies": {
    "KMF": {
      "name": "Comorian franc",
      "symbol": "Fr"
    }
  },
  "gini": {
    "2014": 45.3
  },
  "car": {
    "signs": [
      "COM"
    ],
    "side": "right"
  },
  "startOfWeek": "monday",
  "postalCode": {},
  "idd": {
    "root": "+2",
    "suffixes": [
      "69"
    ]
  },
  "timezones": [
    "UTC+03:00"
  ],
  "flag": "🇰🇲",
  "flags": {
    "png": "https://flagcdn.com/w320/km.png",
    "svg": "https://flagcdn.com/km.svg",
    "alt": "The flag of Comoros is composed of four equal horizontal bands of yellow, white, red and blue, with a green isosceles triangle superimposed on the hoist side of the field. This triangle has its base on the hoist end, spans about two-fifth the width of the field and bears a fly-side facing white crescent and four five-pointed white stars arranged in a vertical line along the opening of the crescent."
  },
  "coatOfArms": {
    "png": "https://mainfacts.com/media/images/coats_of_arms/km.png",
    "svg": "https://mainfacts.com/media/images/coats_of_arms/km.svg"
  },
  "maps": {
    "googleMaps": "https://goo.gl/maps/eas4GP28C1GyStnu6",
    "openStreetMaps": "https://www.openstreetmap.org/relation/535790"
  },
  "translations": {
    "ara": {
      "official": "الإتحاد القمري",
      "common": "جزر القمر"
    },
    "bre": {
      "official": "Unaniezh Komorez",
      "common": "Komorez"
    },
    "ces": {
      "official": "Komorský svaz",
      "common": "Komory"
    },
    "deu": {
      "official": "Union der Komoren",
      "common": "Komoren"
    },
    "est": {
      "official": "Komoori Liit",
      "common": "Komoorid"
    },
    "fin": {
      "official": "Komorien liitto",
      "common": "Komorit"
    },
    "fra": {
      "official": "Union des Comores",
      "common": "Comores"
    },
    "hrv": {
      "official": "Savez Komori",
      "common": "Komori"
    },
    "hun": {
      "official": "Comore-szigeteki Unió",
      "common": "Comore-szigetek"
    },
    "ita": {
      "official": "Unione delle Comore",
      "common": "Comore"
    },
    "jpn": {
      "official": "コモロ連合",
      "common": "コモロ"
    },
    "kor": {
      "official": "코모로 연방",
      "common": "코모로"
    },
    "nld": {
      "official": "Unie van de Comoren",
      "common": "Comoren"
    },
    "per": {
      "official": "مجمع‌الجزایر قمر",
      "common": "اتحاد قُمُر"
    },
    "pol": {
      "official": "Związek Komorów",
      "common": "Komory"
    },
    "por": {
      "official": "União das Comores",
      "common": "Comores"
    },
    "rus": {
      "official": "Союз Коморских Островов",
      "common": "Коморы"
    },
    "slk": {
      "official": "Komorská únia",
      "common": "Komory"
    },
    "spa": {
      "official": "Unión de las Comoras",
      "common": "Comoras"
    },
    "srp": {
      "official": "Unija Komora",
      "common": "Komori"
    },
    "swe": {
      "official": "Unionen Komorerna",
      "common": "Komorerna"
    },
    "tur": {
      "official": "Komorlar Birliği",
      "common": "Komorlar"
    },
    "urd": {
      "official": "اتحاد القمری",
      "common": "القمری"
    },
    "zho": {
      "official": "科摩罗联盟",
      "common": "科摩罗"
    }
  },
  "largest_city": "Moroni",
  "largest_city_local": "Moroni",
  "largest_city_pop": 74749,
  "largest_city_is_capital": true
}